{"nodes": [{"id": "resume", "label": "resume.py", "file_type": "code", "source_file": "app\\schemas\\resume.py", "source_location": "L1"}, {"id": "resume_resumeresponse", "label": "ResumeResponse", "file_type": "code", "source_file": "app\\schemas\\resume.py", "source_location": "L6"}, {"id": "basemodel", "label": "BaseModel", "file_type": "code", "source_file": "", "source_location": ""}, {"id": "resume_config", "label": "Config", "file_type": "code", "source_file": "app\\schemas\\resume.py", "source_location": "L13"}], "edges": [{"source": "resume", "target": "datetime", "relation": "imports_from", "confidence": "EXTRACTED", "source_file": "app\\schemas\\resume.py", "source_location": "L1", "weight": 1.0}, {"source": "resume", "target": "typing", "relation": "imports_from", "confidence": "EXTRACTED", "source_file": "app\\schemas\\resume.py", "source_location": "L2", "weight": 1.0}, {"source": "resume", "target": "pydantic", "relation": "imports_from", "confidence": "EXTRACTED", "source_file": "app\\schemas\\resume.py", "source_location": "L3", "weight": 1.0}, {"source": "resume", "target": "resume_resumeresponse", "relation": "contains", "confidence": "EXTRACTED", "source_file": "app\\schemas\\resume.py", "source_location": "L6", "weight": 1.0}, {"source": "resume_resumeresponse", "target": "basemodel", "relation": "inherits", "confidence": "EXTRACTED", "source_file": "app\\schemas\\resume.py", "source_location": "L6", "weight": 1.0}, {"source": "resume", "target": "resume_config", "relation": "contains", "confidence": "EXTRACTED", "source_file": "app\\schemas\\resume.py", "source_location": "L13", "weight": 1.0}]}